bluefn/__init__.py
bluefn/__main__.py
bluefn/cli/__init__.py
bluefn/cli/blue_cli.py
bluefn/cli/fixtures/__init__.py
bluefn/cli/fixtures/contract_unitest.py
bluefn/conf/__init__.py
bluefn/conf/bluefn_conf.json
bluefn/conf/logger.yml
bluefn/test/__init__.py
bluefn/test/templates_procs.py
bluefn/utils/__init__.py
bluefn/version.py
bluefn-0.1.0.dist-info/entry_points.txt
bluefn-0.1.0.dist-info/WHEEL
bluefn-0.1.0.dist-info/METADATA
bluefn-0.1.0.dist-info/RECORD
